naas_models/__init__.py
naas_models/aimodel_pb2.py
naas_models/asset_pb2.py
naas_models/chat_pb2.py
naas_models/common_pb2.py
naas_models/credit_pb2.py
naas_models/errors_pb2.py
naas_models/iam_pb2.py
naas_models/ontology_pb2.py
naas_models/p2p_validate_pb2.py
naas_models/pydantic/__init__.py
naas_models/pydantic/aimodel_p2p.py
naas_models/pydantic/asset_p2p.py
naas_models/pydantic/chat_p2p.py
naas_models/pydantic/common_p2p.py
naas_models/pydantic/credit_p2p.py
naas_models/pydantic/errors_p2p.py
naas_models/pydantic/iam_p2p.py
naas_models/pydantic/ontology_p2p.py
naas_models/pydantic/registry_p2p.py
naas_models/pydantic/secret_p2p.py
naas_models/pydantic/space_p2p.py
naas_models/pydantic/storage_p2p.py
naas_models/pydantic/workspace_p2p.py
naas_models/registry_pb2.py
naas_models/secret_pb2.py
naas_models/space_pb2.py
naas_models/storage_pb2.py
naas_models/storage_pb2.pyi
naas_models/storage_pb2_grpc.py
naas_models/validate_pb2.py
naas_models/workspace_pb2.py
naas_models/workspace_pb2.pyi
naas_models/workspace_pb2_grpc.py
naas_models-1.29.1.dist-info/METADATA
naas_models-1.29.1.dist-info/WHEEL
naas_models-1.29.1.dist-info/RECORD
